MANIFEST.in
README.md
setup.py
cmsplugin_sections/__init__.py
cmsplugin_sections/cms_plugins.py
cmsplugin_sections/models.py
cmsplugin_sections/unique_slugify.py
cmsplugin_sections.egg-info/PKG-INFO
cmsplugin_sections.egg-info/SOURCES.txt
cmsplugin_sections.egg-info/dependency_links.txt
cmsplugin_sections.egg-info/not-zip-safe
cmsplugin_sections.egg-info/requires.txt
cmsplugin_sections.egg-info/top_level.txt
cmsplugin_sections/migrations/0001_initial.py
cmsplugin_sections/migrations/__init__.py
cmsplugin_sections/migrations_django/0001_initial.py
cmsplugin_sections/migrations_django/__init__.py
cmsplugin_sections/templates/cmsplugin_sections/section-base.html
cmsplugin_sections/templates/cmsplugin_sections/section-container.html
cmsplugin_sections/templates/cmsplugin_sections/section.html